books/__init__.py
books/admin.py
books/apps.py
books/forms.py
books/models.py
books/tests.py
books/urls.py
books/views.py
books/migrations/0001_initial.py
books/migrations/__init__.py
django_books_asl-0.1.dist-info/LICENSE
django_books_asl-0.1.dist-info/METADATA
django_books_asl-0.1.dist-info/WHEEL
django_books_asl-0.1.dist-info/top_level.txt
django_books_asl-0.1.dist-info/RECORD
